smarttime/__init__.py
smarttime-1.0.0.dist-info/licenses/LICENSE
smarttime-1.0.0.dist-info/METADATA
smarttime-1.0.0.dist-info/WHEEL
smarttime-1.0.0.dist-info/top_level.txt
smarttime-1.0.0.dist-info/RECORD
